mylib006/__init__.py
mylib006-0.1.dist-info/LICENSE.txt
mylib006-0.1.dist-info/METADATA
mylib006-0.1.dist-info/WHEEL
mylib006-0.1.dist-info/top_level.txt
mylib006-0.1.dist-info/RECORD
