Metadata-Version: 2.1
Name: mylib006
Version: 0.1
Summary: for calculating square
Home-page: UNKNOWN
Author: Akash
Author-email: akashm7058@gmail.com
License: UNKNOWN
Platform: UNKNOWN
Classifier: Programming Language :: Python :: 3
Classifier: License :: OSI Approved :: MIT License
Classifier: Operating System :: OS Independent
License-File: LICENSE.txt
